Metadata-Version: 2.1
Name: OmniBridge
Version: 0.1.74
Summary: Bridging AI models
Home-page: https://github.com/OmniSpective/OmniBridge
Author: OmniSpective
Author-email: eliran9692@gmail.com
License: Apache License 2.0
License-File: LICENSE
